MANIFEST.in
README.txt
setup.py
propagate/__init__.py
propagate/command_line.py
propagate/cv.py
propagate/data.py
propagate/network.py
propagate/run.py
propagate.egg-info/PKG-INFO
propagate.egg-info/SOURCES.txt
propagate.egg-info/dependency_links.txt
propagate.egg-info/requires.txt
propagate.egg-info/top_level.txt
propagate/test/__init__.py