Metadata-Version: 1.0
Name: propagate
Version: 0.2.1
Summary: Propagation belief graph algorithm
Home-page: https://github.com/atiasnir/propagation
Author: Nir Atias
Author-email: rinatias@gmail.com
License: LICENSE.txt
Keywords: belief propagation diffusion graph algorithm
Platform: UNKNOWN
